lib_typ_parse/__api__.py
lib_typ_parse/__init__.py
lib_typ_parse/typon_client.py
lib_typ_parse/helper/__init__.py
lib_typ_parse/helper/eval_helper.py
lib_typ_parse/helper/eval_service.py
lib_typ_parse/helper/type_resolver.py
lib_typ_parse/parse/__init__.py
lib_typ_parse/parse/parse_L0_skeleton.py
lib_typ_parse/parse/parse_skeleton.py
lib_typ_parse/parse/parser.py
lib_typ_parse/utils/__init__.py
lib_typ_parse/utils/constants.py
lib_typ_parse/utils/exceptions.py
lib_typ_parse/utils/fmt_utils.py
lib_typ_parse/utils/parsing_utils.py
lib_typ_parse/utils/transform_data.py
lib_typ_parse-0.0.4.dist-info/METADATA
lib_typ_parse-0.0.4.dist-info/WHEEL
lib_typ_parse-0.0.4.dist-info/top_level.txt
lib_typ_parse-0.0.4.dist-info/RECORD
