Metadata-Version: 2.1
Name: lib-typ-parse
Version: 0.0.4
Home-page: http://pypi.python.org/pypi/lib_typ_parse/0.0.4
Author: hypothesisbase
Author-email: support@hypothesisbase.com
License: MIT
Requires-Dist: requests
